completo/__init__.py
completo/interfaces.py
completo/py.typed
completo/shortcuts.py
completo/util.py
completo/backends/__init__.py
completo/backends/engine.py
completo/backends/transformers.py
completo/backends/anthropic/__init__.py
completo/backends/anthropic/engine.py
completo/backends/anthropic/transformers.py
completo/backends/openai/__init__.py
completo/backends/openai/engine.py
completo/backends/openai/transformers.py
completo/models/completions.py
completo/models/content.py
completo/models/embeddings.py
completo/models/messages.py
completo/models/tools.py
completo-0.0.10.dist-info/METADATA
completo-0.0.10.dist-info/WHEEL
completo-0.0.10.dist-info/licenses/LICENSE
completo-0.0.10.dist-info/RECORD
