Metadata-Version: 2.4
Name: completo
Version: 0.0.10
Summary: A unified interface for interacting with AI
Project-URL: Repository, https://github.com/rmasters/completo
Project-URL: Issues, https://github.com/rmasters/completo/issues
Project-URL: Changelog, https://github.com/rmasters/completo/releases
Author-email: Ross Masters <ross@rossmasters.com>
License-Expression: MIT
License-File: LICENSE
Keywords: abstraction,ai,generative ai,interface,llm
Classifier: Development Status :: 2 - Pre-Alpha
Classifier: Framework :: Pydantic :: 2
Classifier: Intended Audience :: Developers
Classifier: License :: OSI Approved :: MIT License
Classifier: Programming Language :: Python :: 3.13
Classifier: Typing :: Typed
Requires-Python: >=3.13
Requires-Dist: anthropic>=0.45.2
Requires-Dist: openai>=1.61.1
Requires-Dist: pydantic>=2.10.6
